fulladder.vhdl
library IEEE;
use IEEE.STD_LOGIC_1164.ALL;
 
entity full_adder is Port (
    A : in STD_LOGIC;
    B : in STD_LOGIC;
    Cin : in STD_LOGIC;
    S : out STD_LOGIC;
    Cout : out STD_LOGIC
);
end full_adder;
 
architecture gate_level of full_adder is
 
begin
 
 S <= A XOR B XOR Cin ;
 Cout <= (A AND B) OR (Cin AND A) OR (Cin AND B) ;
 
end gate_level;

fulladder_tb.vhdl
library IEEE;
use ieee.std_logic_1164.all;

entity fulladder_tb is
    end fulladder_tb;

architecture test of fulladder_tb is
    signal a, b, cin: std_logic;
    signal s, cout: std_logic;

    component full_adder
        port(
            a, b, cin: in std_logic;
            s, cout: out std_logic
        );
    end component;
begin
    uut: full_adder port map(a=> a, b=> b, cin => cin, cout=> cout);
    process
    begin
        a <= '0';
        b <= '0';
        cin <= '0';
        wait for 10 ns;

        a <= '1';
        b <= '0';
        cin <= '0';
        wait for 10 ns;

        a <= '0';
        b <= '1';
        cin <= '0';
        wait for 10 ns;

        a <= '1';
        b <= '1';
        cin <= '0';
        wait for 10 ns;

        a <= '0';
        b <= '0';
        cin <= '1';
        wait for 10 ns;

        a <= '1';
        b <= '0';
        cin <= '1';
        wait for 10 ns;

        a <= '0';
        b <= '1';
        cin <= '1';
        wait for 10 ns;

        a <= '1';
        b <= '1';
        cin <= '1';
        wait for 10 ns;

        wait;
    end process;

end test;

result.vcd
$date
  Sat Feb 10 17:38:23 2024
$end
$version
  GHDL v0
$end
$timescale
  1 fs
$end
$scope module standard $end
$upscope $end
$scope module std_logic_1164 $end
$upscope $end
$scope module fulladder_tb $end
$var reg 1 ! a $end
$var reg 1 " b $end
$var reg 1 # cin $end
$var reg 1 $ s $end
$var reg 1 % cout $end
$scope module uut $end
$upscope $end
$upscope $end
$enddefinitions $end
#0
0!
0"
0#
U$
U%
#10000000
1!
#20000000
0!
1"
#30000000
1!
#40000000
0!
0"
1#
#50000000
1!
#60000000
0!
1"
#70000000
1!
