seq1011detector.vhdl
library ieee;
use ieee.std_logic_1164.ALL;

entity seq1011 is Port (
    x : in std_logic; -- input bitstream
    y : out std_logic; -- output port
    clk : in std_logic; -- clock input
    rst : in std_logic; -- reset all states
);
end seq1011;

architecture seq of seq1011 is
    type t_state is (S0, S1, S2, S3, S4); --s0:0, s1:1, s2:10, s3:101, s4:1011
    signal state : t_state;
    
    begin
        process (clk) is
            begin
                if rising_edge(clk) then
                    if rst = 1 then
                        state <= S0;
                        y <= 0;
                    else
                        case state is
                            when SO =>
                                y <= 0;
                                if x = 1 then
                                    state <= S1;
                                end if;
                            when S1 =>
                                y <= 0;
                                if x = 0 then
                                    state <= S2;
                                end if;
                            
                            when S2 =>
                                y <= 0;
                                if x = 0 then
                                    state <= S0;
                                else
                                    state <= S3;
                                end if;
                            
                            when S3 =>
                                if x=1 then
                                    state <= S4;
                                    y <= 1;
                                else
                                    state <= S2;
                                    y <= 0;
                                end if;
                            
                            when S4 =>
                                y <= 0;
                                if x=1 then
                                    state <= S1;
                                else
                                    state <= S2;
                                end if;
                        end case;
                    end if;
                end if;
        end process;
    end seq;

seq/seq1011detector_tb.vhdl
library ieee;
use ieee.std_logic_1164.all;

entity seq1011_tb is
end seq1011_tb;

architecture test of seq1011_tb is
    signal x, y, clk, rst: std_logic;

    component seq1011
        Port (
            x : in std_logic;
            y : out std_logic;
            clk : in std_logic;
            rst : in std_logic
        );
    end component;

begin
    seq1011_inst: seq1011 port map(x => x, y => y, clk => clk, rst => rst);

    process
    begin
        -- Initialize signals
        x <= '0';
        clk <= '0';
        rst <= '1';

        wait for 500 ms;

        -- Release reset
        rst <= '0';

        wait for 1 us;

        -- Apply different input bitstream values
        x <= '1';
        wait for 1 us;
        clk <= '1';
        wait for 1 us;
        clk <= '0';

        wait for 500 ms;

        x <= '0';
        wait for 1 us;
        clk <= '1';
        wait for 1 us;
        clk <= '0';

        wait for 500 ms;

        x <= '1';
        wait for 1 us;
        clk <= '1';
        wait for 1 us;
        clk <= '0';

        wait for 500 ms;

        x <= '1';
        wait for 1 us;
        clk <= '1';
        wait for 1 us;
        clk <= '0';

        wait for 500 ms;

        -- Apply more input values
        x <= '0';
        wait for 1 us;
        clk <= '1';

        -- Add some delay before ending the simulation
        wait for 10 us;
        -- End the simulation
        wait;

    end process;
end test;

seq/result.vcd
$date
  Sat Feb 10 21:33:53 2024
$end
$version
  GHDL v0
$end
$timescale
  1 fs
$end
$scope module standard $end
$upscope $end
$scope module std_logic_1164 $end
$upscope $end
$scope module seq1011_tb $end
$var reg 1 ! x $end
$var reg 1 " y $end
$var reg 1 # clk $end
$var reg 1 $ rst $end
$scope module seq1011_inst $end
$var reg 1 % x $end
$var reg 1 & y $end
$var reg 1 ' clk $end
$var reg 1 ( rst $end
$comment state is not handled $end
$upscope $end
$upscope $end
$enddefinitions $end
#0
0!
U"
0#
1$
0%
U&
0'
1(
#500000000000000
0$
0(
#500001000000000
1!
1%
#500002000000000
0"
1#
0&
1'
#500003000000000
0#
0'
#1000003000000000
0!
0%
#1000004000000000
1#
1'
#1000005000000000
0#
0'
#1500005000000000
1!
1%
#1500006000000000
1#
1'
#1500007000000000
0#
0'
#2000007000000000
#2000008000000000
1"
1#
1&
1'
#2000009000000000
0#
0'
#2500009000000000
0!
0%
#2500010000000000
0"
1#
0&
1'
