jk/jkflipflop.vhdl
library ieee;
use ieee.std_logic_1164.all;

entity jkflipflop is
    Port (
        clk, clr, j, k : in std_logic;
        q, nq : out std_logic
    );
end jkflipflop;

architecture behaviour of jkflipflop is
    signal qt : std_logic;
begin
    process(clk, clr, j, k)
    begin
        if clr = '1' then
            qt <= '0';
        elsif rising_edge(clk) then
            if j = '0' and k = '0' then
                qt <= '0';
            elsif j = '0' and k = '1' then
                qt <= '0';
            elsif j = '1' and k = '0' then
                qt <= '1';
            elsif j = '1' and k = '1' then
                qt <= not qt;
            end if;
        end if;
    end process;

    q <= qt;
    nq <= not qt;
end behaviour;

jk/jkflipflop_tb.vhdl
library ieee;
use ieee.std_logic_1164.all;

entity jkflipflop_tb is
end jkflipflop_tb;

architecture test of jkflipflop_tb is
    signal clk, clr, j, k, q, nq: std_logic;
    component jkflipflop
        port (
            clk, clr, j, k : in std_logic;
            q, nq : out std_logic
        );
    end component;

begin
    jk_flip_flop_inst: jkflipflop port map(clk => clk, clr => clr, j => j, k => k, q => q, nq => nq);

    process
    begin
        -- Initialize signals
        clk <= '0';
        clr <= '0';
        j <= '0';
        k <= '0';

        wait for 500 ms;

        -- Apply clear
        clr <= '1';
        wait for 500 ms;

        -- Release clear and toggle inputs
        clr <= '0';
        j <= '1';
        k <= '0';
        
        wait for 1 us;
        clk <= '1';
        wait for 1 us;
        clk <= '0';
        
        wait for 500 ms;

        -- Toggle inputs to test flip-flop behavior
        j <= '0';
        k <= '1';
        
        wait for 1 us;
        clk <= '1';
        wait for 1 us;
        clk <= '0';

        wait for 500 ms;

        j <= '1';
        k <= '1';

        wait for 1 us;
        clk <= '1';
        wait for 1 us;
        clk <= '0';
        wait for 500 ms;

        j <= '0';
        k <= '0';
	wait for 1 us;
        clk <= '1';
        wait for 1 us;
        clk <= '0';
        wait;

    end process;
end test;

jk/result.vcd
$date
  Mon Feb 19 22:22:35 2024
$end
$version
  GHDL v0
$end
$timescale
  1 fs
$end
$scope module standard $end
$upscope $end
$scope module std_logic_1164 $end
$upscope $end
$scope module jkflipflop_tb $end
$var reg 1 ! clk $end
$var reg 1 " clr $end
$var reg 1 # j $end
$var reg 1 $ k $end
$var reg 1 % q $end
$var reg 1 & nq $end
$scope module jk_flip_flop_inst $end
$var reg 1 ' clk $end
$var reg 1 ( clr $end
$var reg 1 ) j $end
$var reg 1 * k $end
$var reg 1 + q $end
$var reg 1 , nq $end
$var reg 1 - qt $end
$upscope $end
$upscope $end
$enddefinitions $end
#0
0!
0"
0#
0$
U%
U&
0'
0(
0)
0*
U+
U,
U-
#500000000000000
1"
0%
1&
1(
0+
1,
0-
#1000000000000000
0"
1#
0(
1)
#1000001000000000
1!
1%
0&
1'
1+
0,
1-
#1000002000000000
0!
0'
#1500002000000000
0#
1$
0)
1*
#1500003000000000
1!
0%
1&
1'
0+
1,
0-
#1500004000000000
0!
0'
#2000004000000000
1#
1)
#2000005000000000
1!
1%
0&
1'
1+
0,
1-
#2000006000000000
0!
0'
#2500006000000000
0#
0$
0)
0*
#2500007000000000
1!
0%
1&
1'
0+
1,
0-
